steap_by_steap-0.2.1.dist-info/METADATA
steap_by_steap-0.2.1.dist-info/WHEEL
steap_by_steap-0.2.1.dist-info/licenses/LICENSE
steap_by_steap/__init__.py
steap_by_steap/steap_by_steap.cpython-310-x86_64-linux-gnu.so
steap_by_steap-0.2.1.dist-info/RECORD
