Metadata-Version: 2.3
Name: steap_by_steap
Version: 0.2.1
Classifier: Programming Language :: Rust
Classifier: Programming Language :: Python :: Implementation :: CPython
Classifier: Programming Language :: Python :: Implementation :: PyPy
License-File: LICENSE
Summary: A library of some algorithms for python made in rust with pyo3
Requires-Python: >=3.8
